{"nodes": [{"id": "c_users_feres_desktop_esprit_connect_espritconnectfront_src_app_core_models_group_model_ts", "label": "group.model.ts", "file_type": "code", "source_file": "C:\\Users\\feres\\Desktop\\esprit connect\\EspritConnectFront\\src\\app\\core\\models\\group.model.ts", "source_location": "L1"}, {"id": "models_group_model_group", "label": "Group", "file_type": "code", "source_file": "C:\\Users\\feres\\Desktop\\esprit connect\\EspritConnectFront\\src\\app\\core\\models\\group.model.ts", "source_location": "L1"}, {"id": "models_group_model_groupcreaterequest", "label": "GroupCreateRequest", "file_type": "code", "source_file": "C:\\Users\\feres\\Desktop\\esprit connect\\EspritConnectFront\\src\\app\\core\\models\\group.model.ts", "source_location": "L33"}, {"id": "models_group_model_groupprivacy", "label": "GroupPrivacy", "file_type": "code", "source_file": "C:\\Users\\feres\\Desktop\\esprit connect\\EspritConnectFront\\src\\app\\core\\models\\group.model.ts", "source_location": "L60"}], "edges": [{"source": "c_users_feres_desktop_esprit_connect_espritconnectfront_src_app_core_models_group_model_ts", "target": "models_group_model_group", "relation": "contains", "confidence": "EXTRACTED", "source_file": "C:\\Users\\feres\\Desktop\\esprit connect\\EspritConnectFront\\src\\app\\core\\models\\group.model.ts", "source_location": "L1", "weight": 1.0}, {"source": "c_users_feres_desktop_esprit_connect_espritconnectfront_src_app_core_models_group_model_ts", "target": "models_group_model_groupcreaterequest", "relation": "contains", "confidence": "EXTRACTED", "source_file": "C:\\Users\\feres\\Desktop\\esprit connect\\EspritConnectFront\\src\\app\\core\\models\\group.model.ts", "source_location": "L33", "weight": 1.0}, {"source": "c_users_feres_desktop_esprit_connect_espritconnectfront_src_app_core_models_group_model_ts", "target": "models_group_model_groupprivacy", "relation": "contains", "confidence": "EXTRACTED", "source_file": "C:\\Users\\feres\\Desktop\\esprit connect\\EspritConnectFront\\src\\app\\core\\models\\group.model.ts", "source_location": "L60", "weight": 1.0}], "raw_calls": []}